.gitignore
.travis.yml
CHANGES.txt
LICENSE.txt
MANIFEST.in
Makefile
README.rst
extra_requirements.txt
requirements.txt
setup.cfg
setup.py
/home/rowan/projects/gaidaros/bin/run_gaidaros
bin/run_gaidaros
docs/TODO.rst
examples/complex_fictional_example.py
examples/echo_server.py
examples/hello_world.py
gaidaros/__init__.py
gaidaros/gaidaros.py
gaidaros.egg-info/PKG-INFO
gaidaros.egg-info/SOURCES.txt
gaidaros.egg-info/dependency_links.txt
gaidaros.egg-info/top_level.txt
gaidaros/stuff/gaidaros.conf
gaidaros/test/__init__.py
gaidaros/test/test_basic.py