Metadata-Version: 1.1
Name: gaidaros
Version: 0.1.1
Summary: Async server micro-framework for control freaks
Home-page: http://github.com/rowanthorpe/gaidaros
Author: Rowan Thorpe
Author-email: rowan@rowanthorpe.com
License: The MIT License: http://www.opensource.org/licenses/mit-license.php
Download-URL: https://api.github.com/repos/rowanthorpe/gaidaros/tarball/0.1.1
Keywords: async,tcp,server
Platform: UNKNOWN
Classifier: Development Status :: 3 - Alpha
Classifier: Environment :: Other Environment
Classifier: Intended Audience :: Developers
Classifier: License :: OSI Approved :: MIT License
Classifier: Operating System :: POSIX
Classifier: Operating System :: POSIX :: Linux
Classifier: Programming Language :: Python
Classifier: Programming Language :: Python :: 2
Classifier: Programming Language :: Python :: 2.6
Classifier: Programming Language :: Python :: 2.7
Classifier: Programming Language :: Python :: 3
Classifier: Programming Language :: Python :: 3.0
Classifier: Programming Language :: Python :: 3.1
Classifier: Programming Language :: Python :: 3.2
Classifier: Programming Language :: Python :: 3.3
Classifier: Topic :: Internet
Classifier: Topic :: Software Development :: Libraries
Classifier: Topic :: Software Development :: Libraries :: Python Modules
Classifier: Topic :: System :: Clustering
Classifier: Topic :: System :: Hardware :: Symmetric Multi-processing
Classifier: Topic :: System :: Networking
